jupyterhub_inithooks/__init__.py
jupyterhub_roothooks/__init__.py
jupyterhub_roothooks-0.2.1.dist-info/LICENSE
jupyterhub_roothooks-0.2.1.dist-info/METADATA
jupyterhub_roothooks-0.2.1.dist-info/WHEEL
jupyterhub_roothooks-0.2.1.dist-info/entry_points.txt
jupyterhub_roothooks-0.2.1.dist-info/top_level.txt
jupyterhub_roothooks-0.2.1.dist-info/RECORD
