Metadata-Version: 2.1
Name: jupyterhub-roothooks
Version: 0.2.1
Summary: Help run hooks as root before dropping privs & running as unprivileged user
Author: Yuvi Panda
Author-email: yuvipanda@gmail.com
License: UNKNOWN
Platform: UNKNOWN
License-File: LICENSE
Requires-Dist: traitlets
